[
null,
{"id":1,"animationId":6,"description":"","etypeId":1,"traits":[{"code":31,"dataId":1,"value":0},{"code":22,"dataId":0,"value":0}],"iconIndex":97,"name":"剑","note":"","params":[0,0,10,0,0,0,0,0],"price":500,"wtypeId":2},
{"id":2,"animationId":6,"description":"","etypeId":1,"traits":[{"code":31,"dataId":1,"value":0},{"code":22,"dataId":0,"value":0}],"iconIndex":99,"name":"斧","note":"","params":[0,0,10,0,0,0,0,0],"price":500,"wtypeId":4},
{"id":3,"animationId":1,"description":"","etypeId":1,"traits":[{"code":31,"dataId":1,"value":0},{"code":22,"dataId":0,"value":0}],"iconIndex":101,"name":"杖","note":"","params":[0,0,10,0,0,0,0,0],"price":500,"wtypeId":6},
{"id":4,"animationId":11,"description":"","etypeId":1,"traits":[{"code":31,"dataId":1,"value":0},{"code":22,"dataId":0,"value":0}],"iconIndex":102,"name":"弓","note":"","params":[0,0,10,0,0,0,0,0],"price":500,"wtypeId":7},
{"id":5,"animationId":6,"description":"普通的木剑","etypeId":1,"traits":[{"code":31,"dataId":1,"value":0},{"code":22,"dataId":0,"value":0}],"iconIndex":97,"name":"木剑","note":"","params":[0,0,3,0,0,0,0,0],"price":10,"wtypeId":2},
{"id":6,"animationId":1,"description":"哥布林们自己做的武器。","etypeId":1,"traits":[{"code":31,"dataId":1,"value":0},{"code":22,"dataId":0,"value":0}],"iconIndex":110,"name":"骨棒","note":"","params":[0,0,5,0,0,0,0,0],"price":16,"wtypeId":2},
{"id":7,"animationId":1,"description":"染上僵尸毒素的骨棒，攻击力不高，但是百分百使敌人中毒。\n跟班专用武器。","etypeId":1,"traits":[{"code":31,"dataId":1,"value":0},{"code":22,"dataId":0,"value":0},{"code":32,"dataId":4,"value":1}],"iconIndex":97,"name":"哥布林涂毒骨棒","note":"","params":[0,0,4,0,0,0,0,0],"price":50,"wtypeId":13},
{"id":8,"animationId":11,"description":"你爱用的匕首。由于沾上血污变钝了，价值也变低了不少。","etypeId":1,"traits":[{"code":31,"dataId":1,"value":0},{"code":22,"dataId":0,"value":0}],"iconIndex":96,"name":"染血的匕首","note":"","params":[0,0,6,0,0,0,1,0],"price":10,"wtypeId":1},
{"id":9,"animationId":11,"description":"驯犬者的匕首，攻击力很低，但是50%概率暴击。","etypeId":1,"traits":[{"code":31,"dataId":1,"value":0},{"code":22,"dataId":0,"value":0},{"code":22,"dataId":2,"value":0.5}],"iconIndex":96,"name":"驯犬者的匕首","note":"","params":[0,0,1,0,0,0,0,0],"price":40,"wtypeId":1},
{"id":10,"animationId":11,"description":"山贼的涂毒匕首，攻击力很低，但是50%概率使敌人中毒。","etypeId":1,"traits":[{"code":31,"dataId":1,"value":0},{"code":22,"dataId":0,"value":0},{"code":32,"dataId":4,"value":0.5}],"iconIndex":96,"name":"山贼的涂毒匕首","note":"","params":[0,0,1,0,0,0,0,0],"price":40,"wtypeId":1},
{"id":11,"animationId":16,"description":"可以使用百分百命中的技能“精准打击”。跟班武器。","etypeId":1,"traits":[{"code":31,"dataId":1,"value":0},{"code":22,"dataId":0,"value":0},{"code":43,"dataId":16,"value":1}],"iconIndex":21,"name":"猎犬的加护","note":"","params":[0,0,6,0,0,0,4,0],"price":0,"wtypeId":13},
{"id":12,"animationId":0,"description":"","etypeId":1,"traits":[{"code":31,"dataId":1,"value":0},{"code":22,"dataId":0,"value":0}],"iconIndex":0,"name":"","note":"","params":[0,0,0,0,0,0,0,0],"price":0,"wtypeId":0},
{"id":13,"animationId":0,"description":"","etypeId":1,"traits":[{"code":31,"dataId":1,"value":0},{"code":22,"dataId":0,"value":0}],"iconIndex":0,"name":"","note":"","params":[0,0,0,0,0,0,0,0],"price":0,"wtypeId":0},
{"id":14,"animationId":0,"description":"","etypeId":1,"traits":[{"code":31,"dataId":1,"value":0},{"code":22,"dataId":0,"value":0}],"iconIndex":0,"name":"","note":"","params":[0,0,0,0,0,0,0,0],"price":0,"wtypeId":0},
{"id":15,"animationId":0,"description":"","etypeId":1,"traits":[{"code":31,"dataId":1,"value":0},{"code":22,"dataId":0,"value":0}],"iconIndex":0,"name":"","note":"","params":[0,0,0,0,0,0,0,0],"price":0,"wtypeId":0}
]